{
  "id" : "Plant_063-32_SideView90/Day_022.jpg",
  "leaf" : [ {
    "id" : 1,
    "status" : "alive",
    "tip" : {
      "x" : 1339.0,
      "y" : 1720.0
    },
    "collar" : {
      "x" : 1305.0,
      "y" : 1802.0
    }
  }, {
    "id" : 2,
    "status" : "alive",
    "tip" : {
      "x" : 1329.0,
      "y" : 1586.0
    },
    "collar" : {
      "x" : 1303.0,
      "y" : 1722.0
    }
  }, {
    "id" : 3,
    "status" : "alive",
    "tip" : {
      "x" : 1215.0,
      "y" : 1296.0
    },
    "collar" : {
      "x" : 1299.0,
      "y" : 1601.0
    }
  }, {
    "id" : 4,
    "status" : "alive",
    "tip" : {
      "x" : 1477.0,
      "y" : 1331.0
    },
    "collar" : {
      "x" : 1322.0,
      "y" : 1509.0
    }
  }, {
    "id" : 5,
    "status" : "alive",
    "tip" : {
      "x" : 1548.0,
      "y" : 914.0
    },
    "collar" : {
      "x" : 1313.0,
      "y" : 1436.0
    }
  }, {
    "id" : 6,
    "status" : "alive",
    "tip" : {
      "x" : 1617.0,
      "y" : 1079.0
    },
    "collar" : {
      "x" : 1314.0,
      "y" : 1402.0
    }
  }, {
    "id" : 7,
    "status" : "alive",
    "tip" : {
      "x" : 1470.0,
      "y" : 830.0
    },
    "collar" : {
      "x" : 1314.0,
      "y" : 1466.0
    }
  } ],
  "base" : {
    "x" : 1303.0,
    "y" : 1834.0
  }
}